LICENSE
README.md
setup.py
JanexNLG/__init__.py
JanexNLG/libraries.py
JanexNLG/main.py
JanexNLG/neuron.py
JanexNLG/trainer.py
JanexNLG/utils.py
JanexNLG.egg-info/PKG-INFO
JanexNLG.egg-info/SOURCES.txt
JanexNLG.egg-info/dependency_links.txt
JanexNLG.egg-info/requires.txt
JanexNLG.egg-info/top_level.txt